setup.cfg
setup.py
hypermedia_resource/__init__.py
hypermedia_resource/attributes.py
hypermedia_resource/base.py
hypermedia_resource/dom.py
hypermedia_resource/inputs.py
hypermedia_resource/media_types.py
hypermedia_resource/resource.py
hypermedia_resource/translator.py
hypermedia_resource/utils.py
hypermedia_resource/wrappers.py
hypermedia_resource.egg-info/PKG-INFO
hypermedia_resource.egg-info/SOURCES.txt
hypermedia_resource.egg-info/dependency_links.txt
hypermedia_resource.egg-info/top_level.txt
hypermedia_resource/adapters/__init__.py
hypermedia_resource/adapters/hal_json.py
hypermedia_resource/adapters/hale_json.py
hypermedia_resource/contrib/__init__.py
hypermedia_resource/contrib/browser.py
hypermedia_resource/contrib/maze_xml.py