Metadata-Version: 1.0
Name: hypermedia-resource
Version: 0.2.0
Summary: Generic interface for hypermedia messages
Home-page: https://github.com/the-hypermedia-project/hypermedia-resource-python/
Author: Stephen Mizell
Author-email: smizell@gmail.com
License: MIT
Platform: UNKNOWN
